klee/client/__init__.py
klee/client/api/__init__.py
klee/client/api/default/__init__.py
klee/client/api/default/container_create.py
klee/client/api/default/container_inspect.py
klee/client/api/default/container_list.py
klee/client/api/default/container_prune.py
klee/client/api/default/container_remove.py
klee/client/api/default/container_stop.py
klee/client/api/default/container_update.py
klee/client/api/default/exec_create.py
klee/client/api/default/exec_start_web_socket.py
klee/client/api/default/exec_stop.py
klee/client/api/default/image_build.py
klee/client/api/default/image_create.py
klee/client/api/default/image_inspect.py
klee/client/api/default/image_list.py
klee/client/api/default/image_prune.py
klee/client/api/default/image_remove.py
klee/client/api/default/image_tag.py
klee/client/api/default/network_connect.py
klee/client/api/default/network_create.py
klee/client/api/default/network_disconnect.py
klee/client/api/default/network_inspect.py
klee/client/api/default/network_list.py
klee/client/api/default/network_prune.py
klee/client/api/default/network_remove.py
klee/client/api/default/volume_create.py
klee/client/api/default/volume_inspect.py
klee/client/api/default/volume_list.py
klee/client/api/default/volume_prune.py
klee/client/api/default/volume_remove.py
klee/client/client.py
klee/client/errors.py
klee/client/models/__init__.py
klee/client/models/container.py
klee/client/models/container_config.py
klee/client/models/container_config_network_driver.py
klee/client/models/container_config_restart_policy.py
klee/client/models/container_inspect.py
klee/client/models/container_network_driver.py
klee/client/models/container_restart_policy.py
klee/client/models/container_summary.py
klee/client/models/end_point.py
klee/client/models/end_point_config.py
klee/client/models/error_response.py
klee/client/models/exec_config.py
klee/client/models/exec_start_config.py
klee/client/models/id_response.py
klee/client/models/image.py
kleene_cli-0.1.0rc3.dist-info/LICENSE
kleene_cli-0.1.0rc3.dist-info/METADATA
kleene_cli-0.1.0rc3.dist-info/WHEEL
kleene_cli-0.1.0rc3.dist-info/entry_points.txt
kleene_cli-0.1.0rc3.dist-info/RECORD
